dbdev/__init__.py
dbdev/cli.py
dbdev/config.py
dbdev/docker_manager.py
dbdev/logger.py
dbdev-0.1.1.dist-info/METADATA
dbdev-0.1.1.dist-info/WHEEL
dbdev-0.1.1.dist-info/entry_points.txt
dbdev-0.1.1.dist-info/top_level.txt
dbdev-0.1.1.dist-info/RECORD
