Metadata-Version: 2.1
Name: dbdev
Version: 0.1.1
Summary: A CLI tool to automate SQL database container management for developers using Docker.
Home-page: https://github.com/leticiamantovani/dbdev
Author: Leticia Mantovani
Author-email: leticiamantovani159@email.com
Classifier: Programming Language :: Python :: 3
Classifier: License :: OSI Approved :: MIT License
Classifier: Operating System :: OS Independent
Requires-Python: >=3.8
Requires-Dist: docker
Requires-Dist: python-dotenv
Requires-Dist: typer
